shapesimilarity/__init__.py
shapesimilarity/frechetdistance.py
shapesimilarity/geometry.py
shapesimilarity/procrustesanalysis.py
shapesimilarity/shapesimilarity.py
shapesimilarity/utils.py
shapesimilarity-1.0.0.dist-info/METADATA
shapesimilarity-1.0.0.dist-info/WHEEL
shapesimilarity-1.0.0.dist-info/top_level.txt
shapesimilarity-1.0.0.dist-info/RECORD
