Metadata-Version: 2.1
Name: shapesimilarity
Version: 1.0.0
Summary: Quantify the similarity between two shapes/curves
Home-page: https://github.com/nelsonwenner/shape-similarity
Author: Nelson Wenner
Keywords: python,curve,frechet-distance,procrustes-analysis
Platform: any
